promotion_counters/__init__.py
promotion_counters/action.py
promotion_counters/admin.py
promotion_counters/apps.py
promotion_counters/locale/en/LC_MESSAGES/django.po
promotion_counters/locale/ru/LC_MESSAGES/django.po
promotion_counters/migrations/0001_initial.py
promotion_counters/migrations/0002_promotionprogram_enabled.py
promotion_counters/migrations/0003_promotionprogram_repeatable.py
promotion_counters/migrations/0004_auto_20230819_0933.py
promotion_counters/migrations/__init__.py
promotion_counters/models/__init__.py
promotion_counters/models/achievement_counter.py
promotion_counters/models/promotion_program.py
promotion_counters/models/utils.py
promotion_counters/utils.py
django_promotion_counters-0.1.5.dist-info/LICENSE
django_promotion_counters-0.1.5.dist-info/METADATA
django_promotion_counters-0.1.5.dist-info/WHEEL
django_promotion_counters-0.1.5.dist-info/RECORD
