Metadata-Version: 2.1
Name: django-promotion-counters
Version: 0.1.5
Summary: Django app to handle promotion and marketing events.
Author: rukosenpa
Author-email: daniktarasov@gmail.com
Requires-Python: >=3.8
Classifier: Programming Language :: Python :: 3
Classifier: Programming Language :: Python :: 3.8
Classifier: Programming Language :: Python :: 3.9
Classifier: Programming Language :: Python :: 3.10
Classifier: Programming Language :: Python :: 3.11
Requires-Dist: django (==3.2)
Requires-Dist: uuid7 (>=0.1.0,<0.2.0)
